{
  "at": "2026-06-13T07:34:55.996Z",
  "metrics": {
    "J": 15.85030196245859,
    "loss": 0,
    "entropy": 0.4884541949949847,
    "p50": 21.073363999999856
  },
  "samples": [
    {
      "probe": "GH",
      "ms": 22.834243000000015,
      "lost": false
    },
    {
      "probe": "NPM",
      "ms": 10.408226000000013,
      "lost": false
    },
    {
      "probe": "CF",
      "ms": 6.92030299999999,
      "lost": false
    },
    {
      "probe": "VRC",
      "ms": 47.61821800000007,
      "lost": false
    },
    {
      "probe": "GH",
      "ms": 22.500365999999985,
      "lost": false
    },
    {
      "probe": "NPM",
      "ms": 13.84148700000003,
      "lost": false
    },
    {
      "probe": "CF",
      "ms": 7.413659999999936,
      "lost": false
    },
    {
      "probe": "VRC",
      "ms": 44.81394799999998,
      "lost": false
    },
    {
      "probe": "GH",
      "ms": 21.396861999999828,
      "lost": false
    },
    {
      "probe": "NPM",
      "ms": 9.684737000000041,
      "lost": false
    },
    {
      "probe": "CF",
      "ms": 6.024089000000004,
      "lost": false
    },
    {
      "probe": "VRC",
      "ms": 31.82619599999998,
      "lost": false
    },
    {
      "probe": "GH",
      "ms": 21.073363999999856,
      "lost": false
    },
    {
      "probe": "NPM",
      "ms": 8.634453000000121,
      "lost": false
    },
    {
      "probe": "CF",
      "ms": 5.970798000000059,
      "lost": false
    },
    {
      "probe": "VRC",
      "ms": 36.65626400000019,
      "lost": false
    },
    {
      "probe": "GH",
      "ms": 21.490800000000036,
      "lost": false
    },
    {
      "probe": "NPM",
      "ms": 9.753836999999976,
      "lost": false
    },
    {
      "probe": "CF",
      "ms": 6.054665999999997,
      "lost": false
    },
    {
      "probe": "VRC",
      "ms": 27.83191100000022,
      "lost": false
    },
    {
      "probe": "GH",
      "ms": 21.361986999999772,
      "lost": false
    },
    {
      "probe": "NPM",
      "ms": 10.053077999999914,
      "lost": false
    },
    {
      "probe": "CF",
      "ms": 6.3664520000002085,
      "lost": false
    },
    {
      "probe": "VRC",
      "ms": 28.48046199999999,
      "lost": false
    },
    {
      "probe": "GH",
      "ms": 21.31547899999987,
      "lost": false
    },
    {
      "probe": "NPM",
      "ms": 9.701788999999735,
      "lost": false
    },
    {
      "probe": "CF",
      "ms": 5.942986000000019,
      "lost": false
    },
    {
      "probe": "VRC",
      "ms": 30.6957239999997,
      "lost": false
    },
    {
      "probe": "GH",
      "ms": 22.0822790000002,
      "lost": false
    },
    {
      "probe": "NPM",
      "ms": 8.830521999999746,
      "lost": false
    },
    {
      "probe": "CF",
      "ms": 5.990725999999995,
      "lost": false
    },
    {
      "probe": "VRC",
      "ms": 32.74742700000024,
      "lost": false
    },
    {
      "probe": "GH",
      "ms": 21.246470000000045,
      "lost": false
    },
    {
      "probe": "NPM",
      "ms": 9.784114000000045,
      "lost": false
    },
    {
      "probe": "CF",
      "ms": 6.292713999999705,
      "lost": false
    },
    {
      "probe": "VRC",
      "ms": 32.67376899999999,
      "lost": false
    },
    {
      "probe": "GH",
      "ms": 21.639238000000205,
      "lost": false
    },
    {
      "probe": "NPM",
      "ms": 7.9837909999996555,
      "lost": false
    },
    {
      "probe": "CF",
      "ms": 6.406508000000031,
      "lost": false
    },
    {
      "probe": "VRC",
      "ms": 35.88905200000045,
      "lost": false
    },
    {
      "probe": "GH",
      "ms": 21.16091999999935,
      "lost": false
    },
    {
      "probe": "NPM",
      "ms": 8.491836000000148,
      "lost": false
    },
    {
      "probe": "CF",
      "ms": 6.092096000000311,
      "lost": false
    },
    {
      "probe": "VRC",
      "ms": 62.80071700000008,
      "lost": false
    },
    {
      "probe": "GH",
      "ms": 21.33323399999972,
      "lost": false
    },
    {
      "probe": "NPM",
      "ms": 8.65544299999965,
      "lost": false
    },
    {
      "probe": "CF",
      "ms": 6.344420000000355,
      "lost": false
    },
    {
      "probe": "VRC",
      "ms": 28.17120200000045,
      "lost": false
    }
  ]
}