{
  "at": "2026-07-13T09:46:57.009Z",
  "metrics": {
    "J": 14.020983531179901,
    "loss": 0,
    "entropy": 0.4855799653384414,
    "p50": 21.799263999999766
  },
  "samples": [
    {
      "probe": "GH",
      "ms": 23.173230999999987,
      "lost": false
    },
    {
      "probe": "NPM",
      "ms": 10.920546000000002,
      "lost": false
    },
    {
      "probe": "CF",
      "ms": 6.591516000000013,
      "lost": false
    },
    {
      "probe": "VRC",
      "ms": 40.56348700000001,
      "lost": false
    },
    {
      "probe": "GH",
      "ms": 24.342298000000028,
      "lost": false
    },
    {
      "probe": "NPM",
      "ms": 12.989493000000039,
      "lost": false
    },
    {
      "probe": "CF",
      "ms": 5.768127999999933,
      "lost": false
    },
    {
      "probe": "VRC",
      "ms": 35.13212999999996,
      "lost": false
    },
    {
      "probe": "GH",
      "ms": 22.576667000000043,
      "lost": false
    },
    {
      "probe": "NPM",
      "ms": 11.76666699999987,
      "lost": false
    },
    {
      "probe": "CF",
      "ms": 6.03970500000014,
      "lost": false
    },
    {
      "probe": "VRC",
      "ms": 69.55893900000001,
      "lost": false
    },
    {
      "probe": "GH",
      "ms": 22.66469200000006,
      "lost": false
    },
    {
      "probe": "NPM",
      "ms": 11.24599400000011,
      "lost": false
    },
    {
      "probe": "CF",
      "ms": 6.587720000000218,
      "lost": false
    },
    {
      "probe": "VRC",
      "ms": 43.85114900000008,
      "lost": false
    },
    {
      "probe": "GH",
      "ms": 22.186468000000104,
      "lost": false
    },
    {
      "probe": "NPM",
      "ms": 11.68948300000011,
      "lost": false
    },
    {
      "probe": "CF",
      "ms": 5.911435999999867,
      "lost": false
    },
    {
      "probe": "VRC",
      "ms": 31.153243000000202,
      "lost": false
    },
    {
      "probe": "GH",
      "ms": 21.799263999999766,
      "lost": false
    },
    {
      "probe": "NPM",
      "ms": 10.38632699999971,
      "lost": false
    },
    {
      "probe": "CF",
      "ms": 6.802592000000004,
      "lost": false
    },
    {
      "probe": "VRC",
      "ms": 37.54585799999995,
      "lost": false
    },
    {
      "probe": "GH",
      "ms": 22.32732100000021,
      "lost": false
    },
    {
      "probe": "NPM",
      "ms": 11.57113100000015,
      "lost": false
    },
    {
      "probe": "CF",
      "ms": 6.922946000000138,
      "lost": false
    },
    {
      "probe": "VRC",
      "ms": 34.19746200000009,
      "lost": false
    },
    {
      "probe": "GH",
      "ms": 22.360743000000184,
      "lost": false
    },
    {
      "probe": "NPM",
      "ms": 10.838512999999693,
      "lost": false
    },
    {
      "probe": "CF",
      "ms": 6.127868000000035,
      "lost": false
    },
    {
      "probe": "VRC",
      "ms": 39.99783100000013,
      "lost": false
    },
    {
      "probe": "GH",
      "ms": 21.962329999999838,
      "lost": false
    },
    {
      "probe": "NPM",
      "ms": 11.485141000000112,
      "lost": false
    },
    {
      "probe": "CF",
      "ms": 7.6633600000000115,
      "lost": false
    },
    {
      "probe": "VRC",
      "ms": 26.009821999999986,
      "lost": false
    },
    {
      "probe": "GH",
      "ms": 22.14273800000001,
      "lost": false
    },
    {
      "probe": "NPM",
      "ms": 12.24081299999989,
      "lost": false
    },
    {
      "probe": "CF",
      "ms": 7.292096000000129,
      "lost": false
    },
    {
      "probe": "VRC",
      "ms": 27.203973000000587,
      "lost": false
    },
    {
      "probe": "GH",
      "ms": 21.9568390000004,
      "lost": false
    },
    {
      "probe": "NPM",
      "ms": 11.401365000000624,
      "lost": false
    },
    {
      "probe": "CF",
      "ms": 6.404547000000093,
      "lost": false
    },
    {
      "probe": "VRC",
      "ms": 44.33209100000022,
      "lost": false
    },
    {
      "probe": "GH",
      "ms": 22.17124899999999,
      "lost": false
    },
    {
      "probe": "NPM",
      "ms": 10.766821000000164,
      "lost": false
    },
    {
      "probe": "CF",
      "ms": 6.1071179999999,
      "lost": false
    },
    {
      "probe": "VRC",
      "ms": 27.974333000000115,
      "lost": false
    }
  ]
}